acd_unique_package/__init__.py
acd_unique_package/__main__.py
acd_unique_package/names.txt
acd_unique_package/speaker.py
acd_unique_package/speakers/__init__.py
acd_unique_package/speakers/acd.py
acd_unique_package-0.3.3.dist-info/licenses/LICENSE.txt
acd_unique_package-0.3.3.dist-info/METADATA
acd_unique_package-0.3.3.dist-info/WHEEL
acd_unique_package-0.3.3.dist-info/entry_points.txt
acd_unique_package-0.3.3.dist-info/top_level.txt
acd_unique_package-0.3.3.dist-info/RECORD
