Metadata-Version: 2.4
Name: acd_unique_package
Version: 0.3.3
Summary: My unique package
Author-email: ACD <test@test.com>
Maintainer-email: ACD <test@test.com>
License: Copyright 2025 ACD
Project-URL: Homepage, https://github.com/xxx/python-packaging
Project-URL: Documentation, https://github.com/xxx/python-packaging/README.md
Classifier: Programming Language :: Python :: 3.9
Classifier: Programming Language :: Python :: Implementation :: CPython
Classifier: License :: OSI Approved :: BSD License
Classifier: Intended Audience :: Developers
Classifier: Operating System :: POSIX :: Linux
Classifier: Operating System :: Microsoft :: Windows
Classifier: Operating System :: MacOS
Classifier: Operating System :: MacOS :: MacOS X
Requires-Python: >=3.9
License-File: LICENSE.txt
Requires-Dist: colorama~=0.0
Provides-Extra: dev
Requires-Dist: twine; extra == "dev"
Requires-Dist: build; extra == "dev"
Dynamic: license-file
